MANIFEST.in
README.rst
bootstrap.py
buildout.cfg
setup.py
docs/conf.py
docs/index.rst
xbob/__init__.py
xbob.db.verification.utils.egg-info/PKG-INFO
xbob.db.verification.utils.egg-info/SOURCES.txt
xbob.db.verification.utils.egg-info/dependency_links.txt
xbob.db.verification.utils.egg-info/entry_points.txt
xbob.db.verification.utils.egg-info/namespace_packages.txt
xbob.db.verification.utils.egg-info/requires.txt
xbob.db.verification.utils.egg-info/top_level.txt
xbob/db/__init__.py
xbob/db/verification/__init__.py
xbob/db/verification/utils/__init__.py
xbob/db/verification/utils/annotations.py
xbob/db/verification/utils/database.py
xbob/db/verification/utils/file.py
xbob/db/verification/utils/test.py
xbob/db/verification/utils/test_files/eyecenter.pos
xbob/db/verification/utils/test_files/idiap.pos
xbob/db/verification/utils/test_files/named.pos