Metadata-Version: 1.1
Name: xbob.db.verification.utils
Version: 1.0.0
Summary: Utilities for xbob.db verification databases
Home-page: http://pypi.python.org/pypi/xbob.db.verification.utils
Author: Manuel Guenther
Author-email: manuel.guenther@idiap.ch
License: GPLv3
Keywords: bob,xbob,xbob.db,verification
Platform: UNKNOWN
Classifier: Development Status :: 4 - Beta
Classifier: Intended Audience :: Developers
Classifier: License :: OSI Approved :: GNU General Public License v3 (GPLv3)
Classifier: Natural Language :: English
Classifier: Programming Language :: Python
Classifier: Programming Language :: Python :: 3
Classifier: Topic :: Scientific/Engineering :: Artificial Intelligence
